cryio/__init__.py
cryio/_cryio.cp36-win_amd64.pyd
cryio/brukerimage.py
cryio/cbfimage.py
cryio/cryioimage.py
cryio/crysalis.py
cryio/edfimage.py
cryio/esperanto.py
cryio/fit2dmask.py
cryio/mar345image.py
cryio/numpymask.py
cryio/parparser.py
cryio/tools.py
cryio/templates/__init__.py
cryio/templates/templates.py
cryio-2018.5.30.dist-info/METADATA
cryio-2018.5.30.dist-info/RECORD
cryio-2018.5.30.dist-info/WHEEL
cryio-2018.5.30.dist-info/top_level.txt
